nonebot_plugin_llob_master-1.1.1.dist-info/METADATA
nonebot_plugin_llob_master-1.1.1.dist-info/WHEEL
nonebot_plugin_llob_master-1.1.1.dist-info/licenses/LICENSE
nonebot_plugin_llob_master/__init__.py
nonebot_plugin_llob_master/__main__.py
nonebot_plugin_llob_master/config.py
nonebot_plugin_llob_master/db.py
nonebot_plugin_llob_master/models/__init__.py
nonebot_plugin_llob_master/models/ntqq_version.py
nonebot_plugin_llob_master/models/process.py
nonebot_plugin_llob_master/resources/default_config.json
nonebot_plugin_llob_master/resources/index.js
nonebot_plugin_llob_master/utils/__init__.py
nonebot_plugin_llob_master/utils/llob/__init__.py
nonebot_plugin_llob_master/utils/llob/http_proxy.py
nonebot_plugin_llob_master/utils/llob/llob.py
nonebot_plugin_llob_master/utils/llob/llob_install.py
nonebot_plugin_llob_master/utils/llob/llob_path.py
nonebot_plugin_llob_master/utils/llob/llob_update_main.py
nonebot_plugin_llob_master/utils/ntqq/__init__.py
nonebot_plugin_llob_master/utils/ntqq/ntqq.py
nonebot_plugin_llob_master/utils/ntqq/ntqq_path.py
nonebot_plugin_llob_master/utils/ntqq/ntqq_process.py
nonebot_plugin_llob_master/utils/ntqq/ntqq_restart_main.py
nonebot_plugin_llob_master/utils/ntqq/ntqq_update_main.py
nonebot_plugin_llob_master/utils/win32api/__init__.py
nonebot_plugin_llob_master/utils/win32api/gui.py
nonebot_plugin_llob_master/utils/win32api/process.py
nonebot_plugin_llob_master-1.1.1.dist-info/RECORD
