Metadata-Version: 2.1
Name: nonebot_plugin_llob_master
Version: 1.1.1
Summary: Support for managing your LLOB on Windows
Author-Email: KanbeReina <kano.2525@qq.com>
License: MIT
Requires-Python: >=3.10
Requires-Dist: nonebot2>=2.3.3
Requires-Dist: nonebot-plugin-apscheduler>=0.5.0
Requires-Dist: psutil>=6.0.0
Requires-Dist: httpx>=0.27.0
